{
  "slug": "my-dear-machan-song-lyrics-maari-2",
  "id": "tag:blogger.com,1999:blog-933118286952973473.post-4920853528245373535",
  "title": "My Dear Machan Song Lyrics Maari 2",
  "movieName": "",
  "singerName": "",
  "lyricistName": "",
  "musicName": "",
  "actorName": "",
  "published": "2018-12-09T06:18:00.000+05:30",
  "sections": {
    "intro": "",
    "easterEgg": "",
    "faq": ""
  },
  "stanzas": [
    "My Dear Machan Song lyrics comes in Maari 2 movie song track Rowdy Baby.  Below is the lines from Rowdy Baby Song which is composed by Yuvan Shankar Raja.",
    "ஹே என் கோலி சோடாவே<br />என் கறி  குழம்பு<br />உன் குட்டி பப்பி  நான்<br />டேக் மீ டேக் மீ<br />ஹே என் சிலுக்கு சட்ட<br />என் வெயிட்டு கட்ட..<br />லவ் சொட்ட சொட்ட<br />டாக் மீ டாக் மீ<br />மை  டியர் மச்சான்<br />நீ மனசு வச்சா<br />நம்ம உரசிக்கலாம்<br />நெஞ்சு ஜிகு ஜிகு ஜா<br />மை  டியர் ராணி<br />என் ட்ரீம்ல  வா நீ<br />நம்ம ஒண்ணா சேர<br />fire  பத்திகிருச்சா<br />ரா நம்ம பீச்சு<br />பக்கம் போத்தாம்<br />ஒரு டப்பான்  குத்து வேஷத்தாம்<br />நீ என்னுடைய ரவுடி பேபி<br />ரா you're only<br />my girl friendu.<br />I'll give you<br />பூச்செண்டு.<br />we'll make us<br />new trendu baby.<br />போத்தாம்  வேஷத்தாம்<br />ரவுடி பேபி<br />girl friendu<br />பூச்செண்டு<br />ட்ரெண்டு பேபி.<br />ரவுடி பேபி...<br />உன்னால, ஏய் மூடாச்சு<br />my hormone-u<br />balance-u.. damageu..<br />ஏய் காமாச்சி..<br />என் மீனாட்சி...<br />இந்த மாரிக்கும்<br />உன் மேல கண்ணாச்சு..<br />ஒன்னு பிளஸ் ஒன்னு<br />டூ மாமா<br />யு பிளஸ் மீ<br />த்ரீ மாமா<br />அடி ஜான்சி  ராணி<br />என் கிருஷ்ணவேணி<br />I'll buy u pony<br />அத ஓட்டினு வா நீ.<br />என் மந்திரவாதி<br />நீ கேடிக்கு கேடி<br />நான் உண்ணுல பாதி<br />நம்ம செம்ம ஜோடி.<br />ரவுடி பேபி<br />ஏ ரவுடி பேபி<br />ரவுடி பேபி..<br />ரவுடி பேபி.<br />ஹே என் கோலி சோடாவே<br />என் கறி  குழம்பு<br />உன் குட்டி பப்பி  நான்<br />டேக் மீ டேக் மீ<br />ஹே என் சிலுக்கு சட்ட<br />என் வெயிட்டு கட்ட..<br />லவ் சொட்ட சொட்ட<br />டாக் மீ டாக் மீ<br />மை  டியர் மச்சான்<br />நீ மனசு வச்சா<br />நம்ம உரசிக்கலாம்<br />நெஞ்சு ஜிகு ஜிகு ஜா<br />மை  டியர் ராணி<br />என் ட்ரீம்ல  வா நீ<br />நம்ம ஒண்ணா சேர<br />fire  பத்திகிருச்சா<br />ரா நம்ம பீச்சு<br />பக்கம் போத்தாம்<br />ஒரு டப்பான்  குத்து வேஷத்தாம்<br />நீ என்னுடைய ரவுடி பேபி<br />ரா you're only<br />my girl friendu.<br />I'll give you<br />பூச்செண்டு.<br />we'll make us<br />new trendu baby.<br />ரவுடி பேபி<br />ரவுடி பேபி<br />ரவுடி பேபி..<br />ரவுடி பேபி.",
    "<a href=\"https://2.bp.blogspot.com/-7tTXpWxy_-4/W_5AF2qYmII/AAAAAAAAYKU/JHmpNPiudHwOqP78W90N3sQKwcp7UWhfACPcBGAYYCw/s1600/Rowdy%2BBaby%2BSong%2BLyrics.jpg\"></a>"
  ],
  "hasTamilLyrics": false,
  "tamilStanzas": [],
  "hasEnglishLyrics": false,
  "englishStanzas": [],
  "category": [
    "Song:My Dear Machan - Maar 2"
  ],
  "relatedSongs": [],
  "seo": {
    "title": "My Dear Machan Song Lyrics Maari 2",
    "description": "Full My Dear Machan songs lyrics, sharable lyrics snippets,. My Dear Machan Song lyrics comes in Maari 2 movie song track Rowdy Baby.&nbsp; Below is the...",
    "keywords": "My Dear Machan full lyrics,  songs lyrics, My Dear Machan lyrics snippets, My Dear Machan WhatsApp status lyrics snippets, share My Dear Machan lyrics snippets with friends, Tamil lyrics, Tamil songs"
  },
  "thumbnail": null,
  "generatedAt": "2026-02-01T14:30:59.993Z",
  "version": 1,
  "enrichedMetadata": {
    "mood": [
      "upbeat",
      "happy"
    ],
    "songType": [
      "dance number",
      "item number"
    ],
    "occasions": [
      "party",
      "celebration",
      "birthday"
    ],
    "keywords": [
      "maari 2",
      "my dear machan",
      "yuvan shankar raja",
      "upbeat",
      "dance number",
      "2018",
      "tamil song",
      "rowdy baby"
    ],
    "faq": "<div class=\"faq-section\"><h3>Frequently Asked Questions</h3><div class=\"faq-item\"><h4>What is the meaning of the song 'My Dear Machan'?</h4><p>The song conveys a playful and affectionate vibe, celebrating friendship and fun moments.</p></div><div class=\"faq-item\"><h4>What is the context of this song in the movie 'Maari 2'?</h4><p>This song is a lively number that showcases the carefree spirit of the characters, enhancing the film's overall festive atmosphere.</p></div><div class=\"faq-item\"><h4>Who composed the music for 'My Dear Machan'?</h4><p>The music for this song was composed by <strong>Yuvan Shankar Raja</strong>.</p></div><div class=\"faq-item\"><h4>When was 'My Dear Machan' released?</h4><p>The song was released on <strong>December 9, 2018</strong>.</p></div></div>",
    "summary": "In 'My Dear Machan', the characters celebrate their friendship and carefree moments, encapsulating the joyous spirit of youth. The upbeat tempo and catchy lyrics evoke feelings of happiness and excitement, making it a perfect party anthem. This song serves as a reminder of the fun times shared among friends, resonating with anyone who has experienced such bonds. Overall, it adds a vibrant touch to the narrative of <em>Maari 2</em>.",
    "releaseYear": "2018",
    "high_ctr_intro": "<strong>My Dear Machan</strong> from <em>Maari 2</em> is an electrifying dance number that perfectly captures the essence of celebration and joy. With Yuvan Shankar Raja's infectious beats and catchy lyrics, this song is bound to get you on your feet. Experience the vibrant energy and playful vibes that make this track a must-listen!",
    "stanzaMeanings": [
      "My Dear Machan song lyrics are from the Maari 2 movie track Rowdy Baby, composed by Yuvan Shankar Raja.",
      "Hey, my little one, my curry is like your cute puppy. Take me, take me. Hey, my little one, my love is like a sweet song. If you keep your heart open, we can connect. My dear, come into my dreams. Are we on fire? Let's go to the beach and have fun. You are my Rowdy Baby, my only girlfriend. I'll give you flowers, and we'll start a new trend, baby. Rowdy Baby... because of you, my hormones are out of balance. Oh, my love... your eyes are like magic. One plus one is two, and you plus me is three. I'll buy you a pony, come ride it with me. You are my magic, and we are a perfect pair. Rowdy Baby, oh Rowdy Baby, Rowdy Baby... Rowdy Baby.",
      ""
    ]
  }
}
