{
  "id": "tag:blogger.com,1999:blog-933118286952973473.post-7003947773485974691",
  "title": "Thathi Thaavum Paper Naan lyrics -Boss Engira Baskaran songs lyrics",
  "slug": "thathi-thaavum-paper-naan-lyrics-boss_91",
  "stanzas": [
    "<div dir=\"ltr\" style=\"text-align: left;\" trbidi=\"on\"><div style=\"color: #cc0000;\"><b>Singer: </b>Karthik&nbsp; <br /><b>Song: </b>Thathi Thaavum Paper Naan <br /><b>Movie:</b> Boss Engira Baskaran&nbsp; </div><div style=\"color: #cc0000;\"><b>Lyrics : </b>Na Muthukumar </div><br /><span style=\"color: #444444;\">Thathi thaavum paper naan </span><br /><span style=\"color: #444444;\">Ennai boata pola senjaale</span><br /><span style=\"color: #444444;\">Kick yethi yethithaan </span><br /><span style=\"color: #444444;\">Ennai kavuthaale</span><br /><span style=\"color: #444444;\">Inku pona penna naan</span><br /><span style=\"color: #444444;\">Vandhu wine-a oothi ponale</span><br /><span style=\"color: #444444;\">Mappu yethi yethithaan</span><br /><span style=\"color: #444444;\">Mella odhachaale</span>",
    "<span style=\"color: #444444;\">Enna paduren enna psesuren</span><br /><span style=\"color: #444444;\">Ennaku puriya-villai</span><br /><span style=\"color: #444444;\">Engu pogiren enna pannuren</span><br /><span style=\"color: #444444;\">Ennaku theriya-villai</span>",
    "<span style=\"color: #444444;\">Unsondham naan en anbu nee</span><br /><span style=\"color: #444444;\">Un mummy en anti-ee</span><br /><span style=\"color: #444444;\">Un sister-um en brother-pol</span><br /><span style=\"color: #444444;\">Endrume naan vazhalam va va</span>",
    "<span style=\"color: #444444;\">Sattai packet-il vaikira </span><br /><span style=\"color: #444444;\">Cigaratte packet-ah maarura</span><br /><span style=\"color: #444444;\">Heart-u pakkathil sellama</span><br /><span style=\"color: #444444;\">Ceendura-aahhhh</span>",
    "<span style=\"color: #444444;\">Hero honda-va otturen</span><br /><span style=\"color: #444444;\">Hero-polave mathura</span><br /><span style=\"color: #444444;\">Zero pakkathil koduthaan</span><br /><span style=\"color: #444444;\">Podura-aahhhh</span>",
    "<span style=\"color: #444444;\">College poyum therala</span><br /><span style=\"color: #444444;\">Knowledge edhuvum aerala</span><br /><span style=\"color: #444444;\">Marriage panna thevala</span><br /><span style=\"color: #444444;\">Maane udane va</span>",
    "<span style=\"color: #444444;\">Thathi thaavum paper naan </span><br /><span style=\"color: #444444;\">Ennai boata pola senjaale</span><br /><span style=\"color: #444444;\">Kick yethi yethithaan </span><br /><span style=\"color: #444444;\">Ennai kavuthaale</span><br /><span style=\"color: #444444;\">Inku pona penna naan</span><br /><span style=\"color: #444444;\">Vandhu wine-a oothi ponale</span><br /><span style=\"color: #444444;\">Mappu yethi yethithaan</span><br /><span style=\"color: #444444;\">Mella odhachaale</span><br /><span style=\"color: #444444;\">Town-nu bus-ula ariye</span><br /><span style=\"color: #444444;\">Ticket vangi ne neetuna</span><br /><span style=\"color: #444444;\">Vethu ticket-um lottery aagume</span>",
    "<span style=\"color: #444444;\">England-huku raniya</span><br /><span style=\"color: #444444;\">English ne pesina</span><br /><span style=\"color: #444444;\">ABCD-a nesikka thonume</span><br /><span style=\"color: #444444;\">Incomeing calluku kasuilla</span><br /><span style=\"color: #444444;\">Outgoing callukum kasuilla</span><br /><span style=\"color: #444444;\">Un number thavira pesala</span><br /><span style=\"color: #444444;\">Maane udane vaa..</span>",
    "<span style=\"color: #444444;\">Thathi thaavum paper naan ...</span></div>"
  ],
  "tamilStanzas": [],
  "category": [
    "Lyrics:Na Muthukumar",
    "Movie:Boss Engira Baskaran",
    "Music:Yuvan",
    "Singer:Karthik",
    "Song:Thathi Thaavum Paper Naan - Boss Engira Baskaran"
  ],
  "thumbnail": "",
  "published": "2010-08-29T18:39:00.000+05:30",
  "movieName": "Boss Engira Baskaran",
  "singerName": "Karthik",
  "lyricistName": "Na Muthukumar",
  "relatedSongs": [],
  "seo": {
    "title": "Thathi Thaavum Paper Naan lyrics -Boss Engira Baskaran songs lyrics",
    "description": "Thathi Thaavum Paper Naan lyrics -Boss Engira Baskaran songs lyrics - Tamil song lyrics from Boss Engira Baskaran",
    "keywords": "Lyrics:Na Muthukumar, Movie:Boss Engira Baskaran, Music:Yuvan, Singer:Karthik"
  }
}