{
  "slug": "title-track-lyrics-tik-tik-tik",
  "id": "tag:blogger.com,1999:blog-933118286952973473.post-7072288664991318883",
  "title": "Title Track Lyrics Tik Tik Tik ",
  "movieName": "Tik Tik Tik",
  "singerName": "Sunitha Sarathy",
  "lyricistName": "",
  "musicName": "D Imman",
  "actorName": "",
  "published": "2017-12-11T22:34:00.001+05:30",
  "stanzas": [
    "<div>\n<div>\nTik Tik Tik Title Track Lyrics from Tik Tik Tik </div>\n<div>\n<br /></div>\nUn sevigalil<br />\n<div>\nchottu chottena</div>\n<div>\nkaalath thuliyaa ? </div>\n<div>\n<br /></div>\n<div>\nivvadhirvugal </div>\n<div>\nundhan irudhayam</div>\n<div>\nkottum oliyaa?</div>\n<div>\n<br /></div>\n<div>\nevvaththin udhikaana</div>\n<div>\nnee aatrum yedhum</div>\n<div>\nevvaaru inge pizhai?</div>\n<div>\n<br /></div>\n<div>\navvaththin thulimondu</div>\n<div>\n..</div>\n<div>\navvaanil engae mazhai</div>\n<div>\n<br /></div>\n<div>\nvidhi siridhu</div>\n<div>\nmadhi peridhu</div>\n<div>\nthadai siridhu</div>\n<div>\nvidai peridhu</div>\n<div>\n<br /></div>\n<div>\nvali sirudhu</div>\n<div>\nvazhi peridhu</div>\n<div>\nporul siridhu</div>\n<div>\narul peridhu</div>\n<div>\n<br /></div>\n<div>\ntik tik tik ..</div>\n<div>\nUn sevigalil<br />\n<div>\nchottu chottena</div>\n<div>\nkaalath thuliyaa?</div>\n</div>\n<div>\n<br /></div>\n<div>\ntik tik tik ..</div>\n<div>\n<div>\nivvadhirvugal </div>\n<div>\nundhan irudhayam</div>\n<div>\nkottum oliyaa? (2)</div>\n</div>\n<div>\n<br /></div>\n<div>\nmudhal thodangum padi</div>\n<div>\nsarindhu vittaa podhum</div>\n<div>\nkuzhandhaigal pol nirkka</div>\n<div>\npidivadham vendum</div>\n<div>\n<br /></div>\n<div>\niravu vaanathai paar</div>\n<div>\njolikkum natchathiram</div>\n<div>\nangae naam pogalaam vaa</div>\n<div>\nerikulaa ....</div>\n<div>\n<br /></div>\n<div>\nkanavugal nijamaagalaam</div>\n<div>\ndhinamum munnetram adainthaal</div>\n<div>\nnaatilirundhu vinvelikku</div>\n<div>\n...</div>\n<div>\n<br /></div>\n<div>\noadi oadi naadi thaedi</div>\n<div>\nilakku adaivadhu latchiyam</div>\n<div>\nvettriyodu naam thirumbuvomey</div>\n<div>\nuyarvin saththiyam</div>\n<div>\n<br /></div>\n<div>\nnamakkena pala porgal</div>\n<div>\nirukkaiyil</div>\n<div>\nveliyil irundhu oru</div>\n<div>\nvinkal varuvadhaa</div>\n<div>\n<br /></div>\n<div>\nadhai udaithidu</div>\n<div>\nkadhavadaithidu</div>\n<div>\npinnaam poriduvom</div>\n<div>\n<br /></div>\n<div>\nmozhi madha inam</div>\n<div>\npedham irukkaiyil.</div>\n<div>\nnammai azhithida</div>\n<div>\nvaanam vizhuvadhaa</div>\n<div>\n<br /></div>\n<div>\nadhai thaduthidu</div>\n<div>\nkadhai mudithidu</div>\n<div>\npinne naam azhivom</div>\n<div>\n<br /></div>\n<div>\nnurai siridhu</div>\n<div>\nkarai peridhu</div>\n<div>\nthadam siridhu</div>\n<div>\nidam peridhu</div>\n<div>\n<br /></div>\n<div>\nvizhum manadhu</div>\n<div>\nezhum pozhudhu</div>\n<div>\nthuyar siridhu</div>\n<div>\nuyir peridhu</div>\n<div>\n<br /></div>\n<div>\n<div>\ntik tik tik ..</div>\n<div>\nUn sevigalil<br />\n<div>\nchottu chottena</div>\n<div>\nkaalath thuliyaa?</div>\n</div>\n<div>\n<br /></div>\n<div>\ntik tik tik ..</div>\n<div>\n<div>\nivvadhirvugal </div>\n<div>\nundhan irudhayam</div>\n<div>\nkottum oliyaa? (2)</div>\n</div>\n</div>\n<div>\n<br /></div>\n<div>\nabaaya roobangal</div>\n<div>\nboomiyai thaakkinaal</div>\n<div>\naattralin ellaigal</div>\n<div>\nudaithu meeruvom</div>\n<div>\n<br /></div>\n<div>\nanjaadha ullangal</div>\n<div>\nondraaga koodinaal</div>\n<div>\nmarana pidiyai</div>\n<div>\nthaamadham aakkuvom</div>\n<div>\n<br /></div>\n<div>\n<div>\nevvaththin udhikaana</div>\n<div>\nnee aatrum yedhum</div>\n<div>\nevvaaru inge pizhai?</div>\n<div>\n<br /></div>\n<div>\navvaththin thulimondu</div>\n<div>\n..</div>\n<div>\navvaanil engae mazhai</div>\n<div>\n<br /></div>\n<div>\nvidhi siridhu</div>\n<div>\nmadhi peridhu</div>\n<div>\nthadai siridhu</div>\n<div>\nvidai peridhu</div>\n<div>\n<br /></div>\n<div>\nvali sirudhu</div>\n<div>\nvazhi peridhu</div>\n<div>\nporul siridhu</div>\n<div>\narul peridhu</div>\n<div>\n<br /></div>\n<div>\ntik tik tik ..</div>\n<div>\nUn sevigalil<br />\n<div>\nchottu chottena</div>\n<div>\nkaalath thuliyaa?</div>\n</div>\n<div>\n<br /></div>\n<div>\ntik tik tik ..</div>\n<div>\n<div>\nivvadhirvugal </div>\n<div>\nundhan irudhayam</div>\n<div>\nkottum oliyaa? (2)</div>\n</div>\n</div>\n<div>\n<br /></div>\n<div>\nkedigaram naadi thudikkum</div>\n<div>\ntik tik tik</div>\n<div>\nnodiyinai pol</div>\n<div>\noli vedikkum </div>\n<div>\ntik tik tik </div>\n<div>\n<br /></div>\n<div>\navasarathil kadhai </div>\n<div>\nmudippom </div>\n<div>\ntik tik tik </div>\n<div>\n<br /></div>\n<div>\ncoz you know </div>\n<div>\nwhen  we do it</div>\n<div>\nwe do it quick and slick</div>\n<div>\n<br /></div>\n<div>\nnammudan payirichi</div>\n<div>\nthiranin valarchi</div>\n<div>\nmanidhanin pudhi</div>\n<div>\ncan conquer gravity!!</div>\n<div>\nnammul vazhum sakthi</div>\n<div>\nmore than technology</div>\n<div>\nkaatume than nambikkai</div>\n<div>\nvettrik kaana sannadhi</div>\n<div>\n<br /></div>\n<div>\ntik tik tik !!</div>\n<div>\n<br /></div>\n<div>\n<a href=\"https://blogger.googleusercontent.com/img/b/R29vZ2xl/AVvXsEg6HhrnCROLAqjC0G5-1REI2Wyr-aXhPtZ3JxhlhJuE9iZH1KXTl7inIAJA0-qhDS3CfV1s1qDPOTF2iDcjqAtaxGKp33R5bao-vrez2ICjJkvydeiXRM6tI3S0scIgFCD1RPC7UKXLVA/s1600/tiktiktik.jpg\"></a></div>\n<br />\n<div>\n</div>\n<br />\n<div>\n<div>\n<br /></div>\n</div>\n</div>"
  ],
  "hasTamilLyrics": false,
  "tamilStanzas": [],
  "category": [
    "Movie:Tik Tik Tik",
    "Music:D Imman",
    "Singer:Sunitha Sarathy",
    "Singer:Yuvan",
    "Song:Title Track - Tik Tik Tik"
  ],
  "relatedSongs": [
    {
      "id": "tag:blogger.com,1999:blog-933118286952973473.post-7900272312533181303",
      "title": "Tik Tik Tik Song Lyrics",
      "slug": "tik-tik-tik-song-lyrics",
      "thumbnail": "https://blogger.googleusercontent.com/img/b/R29vZ2xl/AVvXsEhYqFsnLl7TM7JQHaFnXhzAaDKv07sdc4suFcfLcez56-ppEf2z-w9Khzf5hYK1qKfelf0cqt1cqMDClC_k9h41AeOxSMn1syvM5zvENPgPj3QSSWA5AZModWQ8hN-WTf6hywp0Gtljvw/s400-c/TSK+%281%29.png",
      "movieName": "Tik Tik Tik",
      "singerName": "Sathish",
      "published": "2018-01-05T21:47:00.002+05:30"
    },
    {
      "id": "tag:blogger.com,1999:blog-933118286952973473.post-8024663331591256541",
      "title": "Kurumba Reprise Lyrics Tik Tik Tik",
      "slug": "kurumba-reprise-lyrics-tik-tik-tik",
      "thumbnail": null,
      "movieName": "Tik Tik Tik",
      "singerName": "Mirthula Siva",
      "published": "2018-01-05T20:29:00.000+05:30"
    },
    {
      "id": "tag:blogger.com,1999:blog-933118286952973473.post-2764979145936544430",
      "title": "Kurumba Song Lyrics Tik Tik Tik",
      "slug": "kurumba-song-lyrics-tik-tik-tik",
      "thumbnail": "https://blogger.googleusercontent.com/img/b/R29vZ2xl/AVvXsEi-imAcmbf8NUPb5OOVy2a2EtELxGMXa3SYJK_XMwbKO-VEO_ZkhNXAicQu9WxnlHRfF7v3LJMr-CPBYYMBsLTP0_ltoyyObCIqJWWKLxSXvwwaEkKu17ZjUugB7JyQ9icS0E0xyvF__ec/s400-c/Kurumba+Lyrics+in+Tamil.jpg",
      "movieName": "Tik Tik Tik",
      "singerName": "Sid Sriram",
      "published": "2018-01-04T20:34:00.003+05:30"
    }
  ],
  "seo": {
    "title": "Title Track Lyrics Tik Tik Tik ",
    "description": "Get the complete Title Track Lyrics Tik Tik Tik  from Tik Tik Tik. composed by D Imman and sung by Sunitha Sarathy. Perfect for fans looking for the full Tamil text and song meaning.",
    "keywords": "Tik Tik Tik, D Imman, Sunitha Sarathy, Yuvan, Tamil lyrics, Tamil songs",
    "structuredData": {
      "@context": "https://schema.org",
      "@type": "MusicRecording",
      "name": "Title Track Lyrics Tik Tik Tik ",
      "description": "Get the complete Title Track Lyrics Tik Tik Tik  from Tik Tik Tik. composed by D Imman and sung by Sunitha Sarathy. Perfect for fans looking for the full Tamil text and song meaning.",
      "inLanguage": "ta",
      "genre": "Tamil Music",
      "datePublished": "2017-12-11T22:34:00.001+05:30",
      "publisher": {
        "@type": "Organization",
        "name": "Tamil Song Lyrics",
        "url": "https://www.tsonglyrics.com"
      },
      "inAlbum": {
        "@type": "MusicAlbum",
        "name": "Tik Tik Tik"
      },
      "byArtist": {
        "@type": "Person",
        "name": "Sunitha Sarathy"
      },
      "composer": {
        "@type": "Person",
        "name": "D Imman"
      }
    }
  },
  "thumbnail": "https://blogger.googleusercontent.com/img/b/R29vZ2xl/AVvXsEg6HhrnCROLAqjC0G5-1REI2Wyr-aXhPtZ3JxhlhJuE9iZH1KXTl7inIAJA0-qhDS3CfV1s1qDPOTF2iDcjqAtaxGKp33R5bao-vrez2ICjJkvydeiXRM6tI3S0scIgFCD1RPC7UKXLVA/s400-c/tiktiktik.jpg",
  "generatedAt": "2026-01-09T17:32:03.570Z",
  "version": 1
}