{
  "slug": "ullala-petta-song-lyrics",
  "id": "tag:blogger.com,1999:blog-933118286952973473.post-6365283106933442056",
  "title": "Ullala Petta Song Lyrics in Tamil",
  "movieName": "Petta",
  "singerName": "",
  "lyricistName": "",
  "musicName": "Anirudh",
  "actorName": "",
  "published": "2018-12-08T23:04:00.001+05:30",
  "stanzas": [
    "<div>\n<br />\nHey ethana santhosam<br />\ndhinamum kottuthu unmela<br />\nnee manasu vachiputta<br />\nrasikka mudiyum unnaala",
    "nee sindhura kanneerum<br />\ninga nerandharam illa<br />\nidha purinjikittaale<br />\ninga neethaanda aala",
    "kanna kattikittu<br />\nellaam iruttunu<br />\nnee koovaatha<br />\nkoovaathappaa",
    "vattam potukittu<br />\nchinna ulagathil<br />\nnee vaazhaatha<br />\nvaazhaathappaa",
    "enna paar naan<br />\nkaiyya thatta<br />\nundaachu ulagam.<br />\nhey naan sonna pakkam<br />\nnikkaama suzhalum",
    "dei en kooda sernthu<br />\nkoothadum nizhalum<br />\nullaara eppodhum<br />\nullaalaa ullaalaa",
    "ribararibbaarey<br />\nribbarey ribararibbaarey<br />\nribararibbaarey<br />\nribbarey ribararibbaarey<br />\nribappa rabapappaa",
    "unakkaaga nillu<br />\nedhuvenum sollu<br />\nsandhosam kodukkaatha<br />\nedhunaalum thallu.",
    "asaraadha dhillu<br />\nirundhaa nee sollu<br />\nen aalu raja nee<br />\nen kooda nillu.",
    "kaiyil kidaichathu<br />\ntholanjaa innum<br />\nromba pudichathu<br />\nkidaikkum.",
    "aanaa.. aasa<br />\nadakkida therinja<br />\nellaam inga<br />\nkaaladiyil kidakkum.",
    "enna paar naan<br />\nkaiyya thatta<br />\nundaachu ulagam.<br />\nhey naan sonna pakkam<br />\nnikkaama suzhalumv",
    "dei en kooda sernthu<br />\nkoothadum nizhalum<br />\nullaara eppodhum<br />\nullaalaa ullaalaa",
    "paar naan<br />\nkaiyya thatta<br />\nundaachu ulagam.<br />\nhey naan sonna pakkam<br />\nnikkaama suzhalum",
    "dei en kooda sernthu<br />\nkoothadum nizhalum<br />\nullaara eppodhum<br />\nullaalaa ullaalaa",
    "hey ethana santhosam<br />\ndhinamum kottuthu unmela<br />\nnee manasu vachiputta<br />\nrasikka mudiyum unnaala",
    "nee sindhura kanneerum<br />\ninga nerandharam illa<br />\nidha purinjikittaale<br />\ninga neethaanda aala",
    "ribararibbaarey<br />\nribbarey ribararibbaarey<br />\nribararibbaarey<br />\nribbarey ribararibbaarey<br />\nribappa rabapappaa",
    "<a href=\"https://blogger.googleusercontent.com/img/b/R29vZ2xl/AVvXsEhQwXc4k7c6JJbVEeAotAVPno4hF0Zcc7P5LgsXw6XVl_a_Ec1PVfbb19vgEihArYgF3UIRENUT_gJdhgaqzVoRZs_TcCURDq3tmSYN4sBlRsUEPAyoJhP7R6jdq9hNV6TVfh-r7IHFvA/s1600/IMG_20181207_170425.jpg\"></a></div>"
  ],
  "hasTamilLyrics": true,
  "tamilStanzas": [
    "<div>\n<br />\nஹே எத்தன சந்தோஷம் <br />\nதினமும் கொட்டுது உன்மேல<br />\nநீ மனசு வச்சிப்புட்டா<br />\nரசிக்க முடியும் உன்னால",
    "நீ சிந்துர கண்ணீரும்<br />\nஇங்க நிரந்தரம் இல்ல<br />\nஇதை புரிஞ்சிக்கிட்டாலே<br />\nஇங்க நீதாண்டா ஆள",
    "கண்ண கட்டிக்கிட்டு<br />\nஎல்லாம் இருட்டுனு<br />\nநீ கூவாத<br />\nகூவாதப்பா",
    "வட்டம் போட்டுக்கிட்டு<br />\nசின்ன உலகத்தில்<br />\nநீ வாழாத<br />\nவாழாதப்பா",
    "என்ன பார்.. நான்<br />\nகைய தட்ட<br />\nஉண்டாச்சு உலகம்.<br />\nஹே நான் சொன்ன பக்கம்<br />\nநிக்காம சுழலும்",
    "டேய் என் கூட சேர்ந்து<br />\nகூத்தாடும் நிழலும்<br />\nஉள்ளார எப்போதும்<br />\nஉல்லாலா உல்லாலா",
    "ரிப்பறிரப்பாரே <br />\nரிப்பரே ரிப்பறிரப்பாரே<br />\nரிப்பறிரப்பாரே <br />\nரிப்பரே ரிப்பறிரப்பாரே<br />\nரிப்பறிரப்பாரே <br />\nரிப்பப்ப ரபபப்பா",
    "உனக்காக நில்லு<br />\nஎதுவெனும் சொல்லு<br />\nசந்தோஷம் கொடுக்காத<br />\nஎதுனாலும் தள்ளு.",
    "அசராத தில்லு<br />\nஇருந்தா நீ சொல்லு<br />\nஎன் ஆளு ராஜா நீ<br />\nஎன் கூட நில்லு.",
    "கையில் கிடைச்சது<br />\nதொலைஞ்சா இன்னும்<br />\nரொம்ப புடிச்சது<br />\nகிடைக்கும்.",
    "ஆனா.. ஆச<br />\nஅடக்கிட தெரிஞ்சா<br />\nஎல்லாம் இங்க<br />\nகாலடியில் கிடக்கும்.",
    "என்ன பார்.. நான்<br />\nகைய தட்ட<br />\nஉண்டாச்சு உலகம்.<br />\nஹே நான் சொன்ன பக்கம்<br />\nநிக்காம சுழலும்",
    "டேய் என் கூட சேர்ந்து<br />\nகூத்தாடும் நிழலும்<br />\nஉள்ளார எப்போதும்<br />\nஉல்லாலா உல்லாலா",
    "பார்.. நான்<br />\nகைய தட்ட<br />\nஉண்டாச்சு உலகம்.<br />\nஹே நான் சொன்ன பக்கம்<br />\nநிக்காம சுழலும்",
    "டேய் என் கூட சேர்ந்து<br />\nகூத்தாடும் நிழலும்<br />\nஉள்ளார எப்போதும்<br />\nஉல்லாலா உல்லாலா",
    "ஹே எத்தன சந்தோஷம்<br />\nதினமும் கொட்டுது உன்மேல<br />\nநீ மனசு வச்சிப்புட்டா<br />\nரசிக்க முடியும் உன்னால",
    "நீ சிந்துர கண்ணீரும்<br />\nஇங்க நிரந்தரம் இல்ல<br />\nஇதை புரிஞ்சிக்கிட்டாலே<br />\nஇங்க நீதாண்டா ஆள",
    "ரிப்பறிரப்பாரே <br />\nரிப்பரே ரிப்பறிரப்பாரே<br />\nரிப்பறிரப்பாரே <br />\nரிப்பரே ரிப்பறிரப்பாரே<br />\nரிப்பறிரப்பாரே <br />\nரிப்பப்ப ரபபப்பா",
    "</div>"
  ],
  "category": [
    "Movie:Petta",
    "Music:Anirudh",
    "Song:Ullaalaa - Petta"
  ],
  "relatedSongs": [
    {
      "id": "tag:blogger.com,1999:blog-933118286952973473.post-4846347881083305092",
      "title": "Petta Paraak Meaning",
      "slug": "petta-paraak-meaning",
      "thumbnail": null,
      "movieName": "Petta",
      "singerName": "",
      "published": "2019-01-16T14:47:00.000+05:30"
    },
    {
      "id": "tag:blogger.com,1999:blog-933118286952973473.post-2572337477755594529",
      "title": "Petta Paraak Song Lyrics in Tamil",
      "slug": "petta-paraak-song-lyrics",
      "thumbnail": "https://blogger.googleusercontent.com/img/b/R29vZ2xl/AVvXsEgo_IH_Rj9AyrfrFKlUjQFthCLkby3r-jJnIodu7_g7Xdanbq_aalRYC7FTfMDjDeHbhEBBO66LBUAfnnCFdc0w4a4TVIvCdBR6wUZfT2PnK7x1dwOQtrvJ4ml2S7xIne0WAcFxnT21lQ8/s400-c/Petta+Paraak+Lyrics.jpg",
      "movieName": "Petta",
      "singerName": "Anirudh",
      "published": "2018-12-15T14:47:00.002+05:30"
    },
    {
      "id": "tag:blogger.com,1999:blog-933118286952973473.post-5710616937572143167",
      "title": "Ilamai Thirumbuthe Lyrics in Tamil",
      "slug": "ilamai-thirumbuthe-lyrics-from-petta",
      "thumbnail": null,
      "movieName": "Petta",
      "singerName": "Anirudh",
      "published": "2018-12-09T22:10:00.001+05:30"
    }
  ],
  "seo": {
    "title": "Ullala Petta Song Lyrics in Tamil",
    "description": "Full Ullaalaa songs lyrics in tamil (ஹே எத்தன சந்தோஷம்&nbsp; தினமும் கொட்டுது ...) Petta Songs Lyrics. sharable lyrics snippets, Music: Anirudh,.",
    "keywords": "Petta, Anirudh, Ullaalaa full lyrics, Petta songs lyrics, Ullaalaa lyrics snippets, Ullaalaa WhatsApp status lyrics snippets, share Ullaalaa lyrics snippets with friends, Tamil lyrics, Tamil songs"
  },
  "thumbnail": "https://blogger.googleusercontent.com/img/b/R29vZ2xl/AVvXsEhQwXc4k7c6JJbVEeAotAVPno4hF0Zcc7P5LgsXw6XVl_a_Ec1PVfbb19vgEihArYgF3UIRENUT_gJdhgaqzVoRZs_TcCURDq3tmSYN4sBlRsUEPAyoJhP7R6jdq9hNV6TVfh-r7IHFvA/s400-c/IMG_20181207_170425.jpg",
  "generatedAt": "2026-01-18T12:42:50.096Z",
  "version": 1
}